{
    "display": {
        "title": {
            "translate": "advancement.tr.rain_rain_go_away.title",
            "color": "white"
        },
        "description": {
            "translate": "advancement.tr.rain_rain_go_away.description",
            "color": "dark_purple"
        },
        "icon": {
            "item": "minecraft:carrot_on_a_stick",
            "nbt": "{CustomModelData:218005}"
        },
        "frame": "task",
        "show_toast": true,
        "announce_to_chat": true,
        "hidden": false
    },
    "criteria": {
        "impossible": {
            "trigger": "minecraft:impossible"
        }
    },
    "parent": "minecraft:adventure/root"
}